ece4078/NotebookChecker.py
ece4078/Utility.py
ece4078/__init__.py
ece4078/install_nginx
ece4078/nginx-meshcat-proxy.conf
ece4078/plotly_viz.py
ece4078/Week02/Renderer.py
ece4078/Week02/__init__.py
ece4078/Week03/Obstacle.py
ece4078/Week03/__init__.py
ece4078/Week03/math_functions.py
ece4078/Week03/path_animation.py
ece4078/Week03/path_search.py
ece4078/gym_simple_gridworlds/__init__.py
ece4078/gym_simple_gridworlds/envs/__init__.py
ece4078/gym_simple_gridworlds/envs/grid_2dplot.py
ece4078/gym_simple_gridworlds/envs/grid_env.py
ece4078/localization/Measurements.py
ece4078/localization/Renderer.py
ece4078/localization/__init__.py
ece4078/localization/dynamic_system_import.py
ece4078/localization/system_310.pyc
ece4078/localization/system_311.pyc
ece4078/localization/system_312.pyc
ece4078/localization/system_38.pyc
ece4078/localization/system_39.pyc
ece4078/localization/template.html
ece4078/localization/images/M0_-2.61_-1.74_.png
ece4078/localization/images/M1_-3.04_-2.97_.png
ece4078/localization/images/M2_-3.49_-2.01_.png
ece4078/localization/images/M3_-3.14_-1.76_.png
ece4078/localization/images/M4_-3.44_-2.75_.png
ece4078/localization/images/M5_-2.20_-2.20_.png
ece4078/localization/images/M6_-2.31_-1.92_.png
ece4078/localization/images/M7_-3.55_-2.35_.png
ece4078/localization/images/M8_-2.60_-2.97_.png
ece4078/localization/images/M9_-2.22_-2.68_.png
ece4078-1.2.3.dist-info/LICENSE
ece4078-1.2.3.dist-info/METADATA
ece4078-1.2.3.dist-info/WHEEL
ece4078-1.2.3.dist-info/top_level.txt
ece4078-1.2.3.dist-info/RECORD
