Metadata-Version: 2.1
Name: ece4078
Version: 1.2.3
Summary: Support file for ece4078 practicals content
Author: Tin Tran
Author-email: tin.tran1@monash.edu
License-File: LICENSE
